{"vocabularies": [{"vocabulary": "publish", "partOfSpeech": "vt.", "chinese": " 出版；刊登；發表"}, {"vocabulary": "publish", "partOfSpeech": "vt.", "chinese": " 發行；刊登；發表"}, {"vocabulary": "publisher", "partOfSpeech": "n.[C]", "chinese": " 出版者（商）；發行者（商）"}, {"vocabulary": "publication", "partOfSpeech": "n.[U]", "chinese": " 出版；發表"}, {"vocabulary": "publication", "partOfSpeech": "n.[C]", "chinese": " 出版物"}, {"vocabulary": "advice", "partOfSpeech": "n.[U]", "chinese": " 忠告；建議"}, {"vocabulary": "advise", "partOfSpeech": "vt. vi.", "chinese": " 勸告；建議"}, {"vocabulary": "adviser", "partOfSpeech": "n.[C]", "chinese": " 顧問"}, {"vocabulary": "encounter", "partOfSpeech": "vt.", "chinese": " 遭遇、遇到（令人不快的事情）"}, {"vocabulary": "encounter", "partOfSpeech": "n.[C]", "chinese": " 相遇；遭遇"}, {"vocabulary": "confront", "partOfSpeech": "vt.", "chinese": " 克服；解決、面臨；面對"}, {"vocabulary": "confrontation", "partOfSpeech": "n. [U C]", "chinese": " 衝突；對抗"}, {"vocabulary": "beloved", "partOfSpeech": "adj.", "chinese": " 心愛的；鍾愛的"}, {"vocabulary": "relevant", "partOfSpeech": "adj.", "chinese": " 有價值的；有意義的、相關的；切題的"}, {"vocabulary": "hostile", "partOfSpeech": "adj.", "chinese": " 敵意的；敵對的"}, {"vocabulary": "hostility", "partOfSpeech": "n. [U]", "chinese": " 敵意；敵視"}, {"vocabulary": "steady", "partOfSpeech": "adj.", "chinese": " 沉著的；穩固的、穩定的；持續的"}, {"vocabulary": "faith", "partOfSpeech": "n. [U]", "chinese": " 信念；信任"}, {"vocabulary": "faithful", "partOfSpeech": "adj.", "chinese": " 忠誠的"}, {"vocabulary": "truthful", "partOfSpeech": "adj.", "chinese": " 坦率的；誠實的"}, {"vocabulary": "hatred", "partOfSpeech": "n.[U]", "chinese": " 仇恨；憎恨"}, {"vocabulary": "dishonesty", "partOfSpeech": "n.[U]", "chinese": " 欺騙；不誠實"}, {"vocabulary": "honesty", "partOfSpeech": "n.[U]", "chinese": " 誠實"}, {"vocabulary": "modest", "partOfSpeech": "adj.", "chinese": " 謙虛的；謙遜的"}, {"vocabulary": "modesty", "partOfSpeech": "n.[U]", "chinese": " 謙虛；謙遜"}, {"vocabulary": "translate", "partOfSpeech": "vt.", "chinese": " 轉換；翻譯"}, {"vocabulary": "translate", "partOfSpeech": "vt. vi.", "chinese": " 翻譯"}, {"vocabulary": "translation", "partOfSpeech": "n.[U]", "chinese": " 翻譯"}, {"vocabulary": "translation", "partOfSpeech": "n.[C]", "chinese": " 譯文；譯作"}, {"vocabulary": "translator", "partOfSpeech": "n.[C]", "chinese": " 譯者"}, {"vocabulary": "rational", "partOfSpeech": "adj.", "chinese": " 理智的；合理的"}, {"vocabulary": "persevere", "partOfSpeech": "vi.", "chinese": " 鍥而不捨；不屈不撓"}, {"vocabulary": "perseverance", "partOfSpeech": "n.[U]", "chinese": " 鍥而不捨；不屈不撓"}, {"vocabulary": "distort", "partOfSpeech": "vt.", "chinese": " 曲解；歪曲"}, {"vocabulary": "deed", "partOfSpeech": "n.[C]", "chinese": " 行為；行動"}, {"vocabulary": "possess", "partOfSpeech": "vt.", "chinese": " 具有；擁有"}, {"vocabulary": "possession", "partOfSpeech": "n.[U]", "chinese": " 具有；擁有"}, {"vocabulary": "possession", "partOfSpeech": "n.[C] usu. pl.", "chinese": " 私人物品"}, {"vocabulary": "indulge", "partOfSpeech": "vi. vt.", "chinese": " （使）沉湎；（使）放縱"}, {"vocabulary": "pity", "partOfSpeech": "n.[U]", "chinese": " 憐憫；同情"}, {"vocabulary": "overtake", "partOfSpeech": "vt.", "chinese": " 突然來襲、降臨"}, {"vocabulary": "inner", "partOfSpeech": "adj.", "chinese": " 內心的、內部的；接近中心的"}, {"vocabulary": "retain", "partOfSpeech": "vt.", "chinese": " 保有；保持"}, {"vocabulary": "foe", "partOfSpeech": "n.[C]", "chinese": " 敵人"}, {"vocabulary": "wealth", "partOfSpeech": "n.[U]", "chinese": " 財富"}, {"vocabulary": "wealth", "partOfSpeech": "adj.", "chinese": " 富有的；富裕的"}, {"vocabulary": "fame", "partOfSpeech": "n.[U]", "chinese": " 名聲"}, {"vocabulary": "virtue", "partOfSpeech": "n.[C]", "chinese": " 美德"}, {"vocabulary": "integrity", "partOfSpeech": "n.[U]", "chinese": " 正直；操守"}, {"vocabulary": "in the face of", "partOfSpeech": "", "chinese": "面臨"}, {"vocabulary": "put an end to sth.", "partOfSpeech": "", "chinese": "終止；停止"}, {"vocabulary": "push forward", "partOfSpeech": "", "chinese": "繼續前進；推進"}, {"vocabulary": "pick oneself up", "partOfSpeech": "", "chinese": "重新振作"}, {"vocabulary": "walk of life", "partOfSpeech": "", "chinese": "行業；社會階層"}, {"vocabulary": "keep in mind", "partOfSpeech": "", "chinese": "記住"}, {"vocabulary": "to the full", "partOfSpeech": "", "chinese": "盡可能；充分地"}, {"vocabulary": "lay out", "partOfSpeech": "", "chinese": "清楚說明"}]}