{"vocabularies": [{"vocabulary": "beggar", "partOfSpeech": "n", "chinese": "乞丐"}, {"vocabulary": "canoe", "partOfSpeech": "n/v", "chinese": "獨木舟"}, {"vocabulary": "lengthen", "partOfSpeech": "v", "chinese": "加長"}, {"vocabulary": "linen", "partOfSpeech": "n", "chinese": "亞麻布製品(如床單/桌巾/內衣等)"}, {"vocabulary": "lipstick", "partOfSpeech": "n", "chinese": "口紅"}, {"vocabulary": "loosen", "partOfSpeech": "v", "chinese": "鬆開"}, {"vocabulary": "memorize", "partOfSpeech": "v", "chinese": "記住"}, {"vocabulary": "memorial", "partOfSpeech": "adj/n", "chinese": "紀念性的；紀念物、碑、館"}, {"vocabulary": "memorable", "partOfSpeech": "adj", "chinese": "難忘的"}, {"vocabulary": "commemorate", "partOfSpeech": "v", "chinese": "紀念"}, {"vocabulary": "millionaire", "partOfSpeech": "n", "chinese": "百萬富翁"}, {"vocabulary": "overcoat", "partOfSpeech": "n", "chinese": "外套、大衣"}, {"vocabulary": "paw", "partOfSpeech": "n/v", "chinese": "腳爪;爪子"}, {"vocabulary": "spade", "partOfSpeech": "n", "chinese": "鏟子/黑桃"}, {"vocabulary": "tortoise", "partOfSpeech": "n", "chinese": "陸龜"}, {"vocabulary": "twig", "partOfSpeech": "n", "chinese": "小樹枝"}, {"vocabulary": "yawn", "partOfSpeech": "n/v", "chinese": "打呵欠"}, {"vocabulary": "mill", "partOfSpeech": "n/v", "chinese": "磨碎機、磨坊；研磨"}, {"vocabulary": "quarrel", "partOfSpeech": "v/n", "chinese": "爭吵"}, {"vocabulary": "quarrelsome", "partOfSpeech": "adj", "chinese": "喜歡爭吵的"}, {"vocabulary": "fax", "partOfSpeech": "n/v", "chinese": "傳真"}, {"vocabulary": "bandage", "partOfSpeech": "n/v", "chinese": "繃帶；用繃帶包紮"}, {"vocabulary": "broom", "partOfSpeech": "n", "chinese": "掃帚"}, {"vocabulary": "crunchy", "partOfSpeech": "adj", "chinese": "鬆脆的"}, {"vocabulary": "crunch", "partOfSpeech": "v/n", "chinese": "咬的喀滋作響/嘎吱地踩過；嘎吱聲"}, {"vocabulary": "diligent", "partOfSpeech": "adj", "chinese": "勤勉的"}, {"vocabulary": "diligence", "partOfSpeech": "n", "chinese": "勤奮"}, {"vocabulary": "dodge", "partOfSpeech": "v/n", "chinese": "閃躲"}, {"vocabulary": "drowsy", "partOfSpeech": "adj", "chinese": "昏昏欲睡的"}, {"vocabulary": "drowsiness", "partOfSpeech": "n", "chinese": "嗜睡"}, {"vocabulary": "hawk", "partOfSpeech": "n", "chinese": "獵鷹/鷹派"}, {"vocabulary": "hive", "partOfSpeech": "n", "chinese": "蜂窩"}, {"vocabulary": "hush", "partOfSpeech": "n/v", "chinese": "肅靜、沈默"}, {"vocabulary": "kettle", "partOfSpeech": "n", "chinese": "茶壺、水壺"}, {"vocabulary": "knob", "partOfSpeech": "n", "chinese": "物體表面或一端的球狀物/球形把手"}, {"vocabulary": "peep", "partOfSpeech": "n/v", "chinese": "窺視"}, {"vocabulary": "pickle", "partOfSpeech": "n/v", "chinese": "醃菜/泡菜；醃"}, {"vocabulary": "plum", "partOfSpeech": "n", "chinese": "李子;梅子"}, {"vocabulary": "plum blossom", "partOfSpeech": " ", "chinese": "梅花"}, {"vocabulary": "raisin", "partOfSpeech": "n", "chinese": "葡萄乾"}, {"vocabulary": "plumber", "partOfSpeech": "n", "chinese": "水管工人"}, {"vocabulary": "plumbing", "partOfSpeech": "n", "chinese": "水管工程"}, {"vocabulary": "riddle", "partOfSpeech": "n", "chinese": "謎語"}, {"vocabulary": "robber", "partOfSpeech": "n", "chinese": "搶匪"}, {"vocabulary": "rusty", "partOfSpeech": "adj", "chinese": "生鏽的/生疏的"}, {"vocabulary": "scoop", "partOfSpeech": "n/v", "chinese": "鏟子/勺子；舀取/挖空"}, {"vocabulary": "sew", "partOfSpeech": "v", "chinese": "縫"}, {"vocabulary": "skyscraper", "partOfSpeech": "n", "chinese": "摩天大樓"}]}