{"vocabularies": [{"vocabulary": "salmon", "partOfSpeech": "n.", "chinese": "鮭魚（單複數同形）"}, {"vocabulary": "tuna", "partOfSpeech": "n.", "chinese": "鮪魚（單複數同形）"}, {"vocabulary": "undergraduate", "partOfSpeech": "n.", "chinese": "大學生"}, {"vocabulary": "undergraduate", "partOfSpeech": "adj.", "chinese": "大學部的"}, {"vocabulary": "framework", "partOfSpeech": "n.", "chinese": "架構，構造"}, {"vocabulary": "notify", "partOfSpeech": "v.", "chinese": "通知，告知"}, {"vocabulary": "transparent", "partOfSpeech": "adj.", "chinese": "透明的"}, {"vocabulary": "novelty", "partOfSpeech": "n.", "chinese": "新奇（不可數），新奇的事物（可數）"}, {"vocabulary": "outsider", "partOfSpeech": "n.", "chinese": "外人，局外人"}, {"vocabulary": "wrongdoing", "partOfSpeech": "n.", "chinese": "惡行"}, {"vocabulary": "contagious", "partOfSpeech": "adj.", "chinese": "有傳染性的"}, {"vocabulary": "decay", "partOfSpeech": "v./n.", "chinese": "腐爛，侵蝕"}, {"vocabulary": "tick", "partOfSpeech": "v.", "chinese": "發出滴答聲，打勾"}, {"vocabulary": "tip", "partOfSpeech": "v.", "chinese": "撕"}, {"vocabulary": "tip", "partOfSpeech": "n.", "chinese": "裂縫，裂口"}, {"vocabulary": "prohibit", "partOfSpeech": "vt.", "chinese": "禁止"}, {"vocabulary": "fleet", "partOfSpeech": "n.", "chinese": "艦隊，隊伍"}, {"vocabulary": "habitat", "partOfSpeech": "n.", "chinese": "棲息地"}, {"vocabulary": "coherent", "partOfSpeech": "adj.", "chinese": "連貫的，前後一致有條理的"}, {"vocabulary": "sheer", "partOfSpeech": "adj.", "chinese": "完全的，純然的"}, {"vocabulary": "sheer", "partOfSpeech": "adv.", "chinese": "陡峭地"}, {"vocabulary": "intact", "partOfSpeech": "adj.", "chinese": "完整無缺的"}, {"vocabulary": "fragment", "partOfSpeech": "n.", "chinese": "碎片，片段"}, {"vocabulary": "fragment", "partOfSpeech": "vi.", "chinese": "使破碎"}, {"vocabulary": "metaphor", "partOfSpeech": "n.", "chinese": "隱喻"}, {"vocabulary": "acquisition", "partOfSpeech": "n.", "chinese": "獲得，添購的物品，收購"}, {"vocabulary": "unlock", "partOfSpeech": "vt.", "chinese": "開鎖，揭開"}, {"vocabulary": "acute", "partOfSpeech": "adj.", "chinese": "敏銳的，急性的，嚴重的"}, {"vocabulary": "chronic", "partOfSpeech": "adj.", "chinese": "慢性的，長期的"}, {"vocabulary": "pension", "partOfSpeech": "n.", "chinese": "退休金，養老金"}, {"vocabulary": "disapprove", "partOfSpeech": "vt.", "chinese": "駁回"}, {"vocabulary": "disapprove", "partOfSpeech": "vi.", "chinese": "反對"}, {"vocabulary": "foster", "partOfSpeech": "vt.", "chinese": "促進，培養"}, {"vocabulary": "foster", "partOfSpeech": "adj.", "chinese": "收養的"}, {"vocabulary": "rebellion", "partOfSpeech": "n.", "chinese": "叛亂，暴動"}, {"vocabulary": "breakthrough", "partOfSpeech": "n.", "chinese": "突破"}, {"vocabulary": "threshold", "partOfSpeech": "n.", "chinese": "門檻，開端"}, {"vocabulary": "prejudice", "partOfSpeech": "n.", "chinese": "偏見"}, {"vocabulary": "prejudice", "partOfSpeech": "vt.", "chinese": "使有偏見"}, {"vocabulary": "stability", "partOfSpeech": "n.", "chinese": "穩定（性）"}, {"vocabulary": "provoke", "partOfSpeech": "vt.", "chinese": "引發，激怒"}, {"vocabulary": "investigator", "partOfSpeech": "n.", "chinese": "調查員"}, {"vocabulary": "consultation", "partOfSpeech": "n.", "chinese": "諮商會"}, {"vocabulary": "donate", "partOfSpeech": "v.", "chinese": "捐贈，捐獻"}, {"vocabulary": "donation", "partOfSpeech": "n.", "chinese": "捐贈，捐贈物"}, {"vocabulary": "donor", "partOfSpeech": "n.", "chinese": "捐贈者"}, {"vocabulary": "transmission", "partOfSpeech": "n.", "chinese": "傳送，傳播"}, {"vocabulary": "slot", "partOfSpeech": "n.", "chinese": "投幣口，時段"}, {"vocabulary": "slot", "partOfSpeech": "vt.", "chinese": "投入狹長孔中"}, {"vocabulary": "resemblance", "partOfSpeech": "n.", "chinese": "相似"}, {"vocabulary": "respondent", "partOfSpeech": "n.", "chinese": "答覆者，應答者"}]}