{"vocabularies": [{"vocabulary": "convert", "partOfSpeech": "v.", "chinese": "轉變；皈依"}, {"vocabulary": "conversion", "partOfSpeech": "n.", "chinese": "轉變"}, {"vocabulary": "vague", "partOfSpeech": "adj.", "chinese": "模糊的"}, {"vocabulary": "blur", "partOfSpeech": "v.", "chinese": "（使）模糊"}, {"vocabulary": "blur", "partOfSpeech": "n.", "chinese": "模糊的事物"}, {"vocabulary": "cling", "partOfSpeech": "v.", "chinese": "緊抓；堅守"}, {"vocabulary": "grip", "partOfSpeech": "vt.", "chinese": "緊握；吸引"}, {"vocabulary": "grip", "partOfSpeech": "n.", "chinese": "緊握；理解"}, {"vocabulary": "snatch", "partOfSpeech": "vt.", "chinese": "奪取、抓住"}, {"vocabulary": "snatch", "partOfSpeech": "n.", "chinese": "片段"}, {"vocabulary": "acknowledge", "partOfSpeech": "v.", "chinese": "承認"}, {"vocabulary": "acknowledgement", "partOfSpeech": "n.", "chinese": "承認；致謝"}, {"vocabulary": "storage", "partOfSpeech": "n.", "chinese": "儲藏"}, {"vocabulary": "document", "partOfSpeech": "n.", "chinese": "文件"}, {"vocabulary": "document", "partOfSpeech": "vt.", "chinese": "記錄"}, {"vocabulary": "documentary", "partOfSpeech": "adj.", "chinese": "文件的；記錄的"}, {"vocabulary": "documentary", "partOfSpeech": "n.", "chinese": "紀錄片"}, {"vocabulary": "reverse", "partOfSpeech": "vt.", "chinese": "推翻；使相反"}, {"vocabulary": "reverse", "partOfSpeech": "adj.", "chinese": "顛倒的，相反的"}, {"vocabulary": "reverse", "partOfSpeech": "n.", "chinese": "相反；背面"}, {"vocabulary": "widespread", "partOfSpeech": "adj.", "chinese": "廣泛的；普遍的"}, {"vocabulary": "frontier", "partOfSpeech": "n.", "chinese": "邊境；邊疆"}, {"vocabulary": "undoubtedly", "partOfSpeech": "adv.", "chinese": "無庸置疑地"}, {"vocabulary": "stain", "partOfSpeech": "v.", "chinese": "玷污，敗壞"}, {"vocabulary": "stain", "partOfSpeech": "n.", "chinese": "污點"}, {"vocabulary": "specimen", "partOfSpeech": "n.", "chinese": "樣品；標本；樣本"}, {"vocabulary": "circuit", "partOfSpeech": "n.", "chinese": "一圈，一周；電路"}, {"vocabulary": "myth", "partOfSpeech": "n.", "chinese": "神話，迷思，錯誤的想法"}, {"vocabulary": "enthusiastic", "partOfSpeech": "adj.", "chinese": "熱心的，熱情的"}, {"vocabulary": "rail", "partOfSpeech": "n.", "chinese": "鐵路，欄杆，扶手"}, {"vocabulary": "condemn", "partOfSpeech": "v.", "chinese": "譴責"}, {"vocabulary": "ceremony", "partOfSpeech": "n.", "chinese": "典禮"}, {"vocabulary": "ragged", "partOfSpeech": "adj.", "chinese": "破爛的；不整潔的"}, {"vocabulary": "scramble", "partOfSpeech": "v.n.", "chinese": "搶奪；爬行"}, {"vocabulary": "scramble", "partOfSpeech": "vt.", "chinese": "倉促做；炒(蛋)"}, {"vocabulary": "server", "partOfSpeech": "n.", "chinese": "伺服器，服務生"}, {"vocabulary": "memo", "partOfSpeech": "n.", "chinese": "備忘錄"}, {"vocabulary": "meddle", "partOfSpeech": "v.", "chinese": "干涉"}, {"vocabulary": "stew", "partOfSpeech": "v.", "chinese": "煮，燉"}, {"vocabulary": "stew", "partOfSpeech": "n.", "chinese": "燉的食物"}, {"vocabulary": "decline", "partOfSpeech": "v.", "chinese": "婉拒"}, {"vocabulary": "decline", "partOfSpeech": "vi.n.", "chinese": "下跌"}, {"vocabulary": "conceive", "partOfSpeech": "v.", "chinese": "構思，設想；懷孕"}, {"vocabulary": "conception", "partOfSpeech": "n.", "chinese": "看法；觀念；懷孕"}, {"vocabulary": "inevitable", "partOfSpeech": "adj.", "chinese": "無法避免的，必然的"}, {"vocabulary": "variable", "partOfSpeech": "adj.", "chinese": "多變的"}, {"vocabulary": "variable", "partOfSpeech": "n.", "chinese": "變數、可變因素"}, {"vocabulary": "variation", "partOfSpeech": "n.", "chinese": "變化，變動"}, {"vocabulary": "undergo", "partOfSpeech": "vt.", "chinese": "經歷，接受"}, {"vocabulary": "senator", "partOfSpeech": "n.", "chinese": "參議員"}, {"vocabulary": "sponsor", "partOfSpeech": "n.", "chinese": "贊助商"}, {"vocabulary": "sponsor", "partOfSpeech": "vt.", "chinese": "贊助"}, {"vocabulary": "sponsorship", "partOfSpeech": "n.", "chinese": "贊助"}, {"vocabulary": "jury", "partOfSpeech": "n.", "chinese": "陪審團"}, {"vocabulary": "convict", "partOfSpeech": "v.", "chinese": "定罪"}, {"vocabulary": "convict", "partOfSpeech": "n.", "chinese": "囚犯"}, {"vocabulary": "conviction", "partOfSpeech": "n.", "chinese": "定罪，信念"}]}