{"vocabularies": [{"vocabulary": "director", "partOfSpeech": "n.[C]", "chinese": "導演"}, {"vocabulary": "documentary", "partOfSpeech": "n.[C]", "chinese": "紀錄片"}, {"vocabulary": "industry", "partOfSpeech": "n.[C]", "chinese": "產業"}, {"vocabulary": "photographer", "partOfSpeech": "n. C]", "chinese": "攝影師"}, {"vocabulary": "capture", "partOfSpeech": "vt.", "chinese": "拍攝"}, {"vocabulary": "proof", "partOfSpeech": "n.[U]", "chinese": "證據"}, {"vocabulary": "damage", "partOfSpeech": "n.[U]", "chinese": "損害；傷害"}, {"vocabulary": "effect", "partOfSpeech": "n.[C] ", "chinese": "影響"}, {"vocabulary": "conservation", "partOfSpeech": "n.[U]", "chinese": "保護"}, {"vocabulary": "record", "partOfSpeech": "vt.", "chinese": "記錄"}, {"vocabulary": "disaster", "partOfSpeech": "n.[C]", "chinese": "災難"}, {"vocabulary": "bury", "partOfSpeech": "vt.", "chinese": "掩埋"}, {"vocabulary": "shed", "partOfSpeech": "vt.", "chinese": "流下"}, {"vocabulary": "prevent", "partOfSpeech": "vt.", "chinese": "預防；阻止"}, {"vocabulary": "tragedy", "partOfSpeech": "n.[C]", "chinese": "悲劇"}, {"vocabulary": "masterpiece", "partOfSpeech": "n.[C] ", "chinese": "傑作"}, {"vocabulary": "scenery", "partOfSpeech": "n.[U]", "chinese": "風景；景色"}, {"vocabulary": "impact", "partOfSpeech": "n. usually sing.", "chinese": "影響"}, {"vocabulary": "grateful", "partOfSpeech": "adj.", "chinese": "感激的"}, {"vocabulary": "start out", "partOfSpeech": "", "chinese": "開始"}, {"vocabulary": "no longer", "partOfSpeech": "", "chinese": "不再"}, {"vocabulary": "on the contrary", "partOfSpeech": "", "chinese": "相反地"}, {"vocabulary": "tear at one's heart", "partOfSpeech": "", "chinese": "使某人傷心欲絕"}, {"vocabulary": "pay off", "partOfSpeech": "", "chinese": "得到回報"}]}