{"vocabularies": [{"vocabulary": "faith", "partOfSpeech": "n", "chinese": "信心;信任"}, {"vocabulary": "aware", "partOfSpeech": "adj", "chinese": "知道的;察覺的"}, {"vocabulary": "awareness", "partOfSpeech": "n", "chinese": "意識"}, {"vocabulary": "considerable", "partOfSpeech": "adj", "chinese": "相當多的"}, {"vocabulary": "pub", "partOfSpeech": "n", "chinese": "酒館；酒吧"}, {"vocabulary": "inform", "partOfSpeech": "vt", "chinese": "通知；告知"}, {"vocabulary": "immediate", "partOfSpeech": "adj", "chinese": "立即的"}, {"vocabulary": "signal", "partOfSpeech": "n/vt", "chinese": "信號;發信號"}, {"vocabulary": "civil", "partOfSpeech": "adj", "chinese": "公民的;民事的"}, {"vocabulary": "govern", "partOfSpeech": "vt", "chinese": "統治，治理"}, {"vocabulary": "perform", "partOfSpeech": "vt", "chinese": "表演;履行;執行;表現"}, {"vocabulary": "performance", "partOfSpeech": "n", "chinese": "表演;表現"}, {"vocabulary": "express", "partOfSpeech": "adj", "chinese": "快速的"}, {"vocabulary": "expressive", "partOfSpeech": "adj", "chinese": "善於表達的"}, {"vocabulary": "expression", "partOfSpeech": "n", "chinese": "表達；表情；用語"}, {"vocabulary": "familiar", "partOfSpeech": "adj", "chinese": "熟悉的"}, {"vocabulary": "previous", "partOfSpeech": "adj", "chinese": "先前的、以前的"}, {"vocabulary": "background", "partOfSpeech": "n", "chinese": "背景"}, {"vocabulary": "aside", "partOfSpeech": "adv", "chinese": "一旁地"}, {"vocabulary": "decade", "partOfSpeech": "n", "chinese": "十年"}, {"vocabulary": "relief", "partOfSpeech": "n", "chinese": "解脫;解除;紓解"}, {"vocabulary": "(much) to one's relief", "partOfSpeech": "", "chinese": "讓某人(大大地)鬆了一口氣"}, {"vocabulary": "neighborhood", "partOfSpeech": "", "chinese": "鄰近地區"}, {"vocabulary": "gather", "partOfSpeech": "v", "chinese": "聚集;收集"}, {"vocabulary": "collection", "partOfSpeech": "", "chinese": "收藏品"}, {"vocabulary": "significant", "partOfSpeech": "adj", "chinese": "重要的；顯著的"}, {"vocabulary": "fair", "partOfSpeech": "n", "chinese": "博覽會；市集"}, {"vocabulary": "fair", "partOfSpeech": "adj", "chinese": "公平的;公正的;正大光明的"}, {"vocabulary": "achieve", "partOfSpeech": "vt", "chinese": "完成;達到;取得;實現"}, {"vocabulary": "achievement", "partOfSpeech": "n", "chinese": "成就"}, {"vocabulary": "resource", "partOfSpeech": "n", "chinese": "資源"}, {"vocabulary": "imagine", "partOfSpeech": "vt", "chinese": "想像"}, {"vocabulary": "imagination", "partOfSpeech": "n", "chinese": "想像力"}, {"vocabulary": "motor", "partOfSpeech": "n", "chinese": "馬達"}, {"vocabulary": "engage", "partOfSpeech": "vt", "chinese": "訂婚"}, {"vocabulary": "engage in", "partOfSpeech": "", "chinese": "從事"}, {"vocabulary": "capable", "partOfSpeech": "adj", "chinese": "有能力的"}, {"vocabulary": "portion", "partOfSpeech": "n", "chinese": "一部分"}, {"vocabulary": "passage", "partOfSpeech": "n", "chinese": "通道;一段"}, {"vocabulary": "survive", "partOfSpeech": "vi/vt", "chinese": "存活;經歷~還活著"}, {"vocabulary": "survivor", "partOfSpeech": "n", "chinese": "生還者"}, {"vocabulary": "reasonable", "partOfSpeech": "adj", "chinese": "合理的，有理由的"}, {"vocabulary": "headquarters", "partOfSpeech": "n", "chinese": "總部、總公司"}, {"vocabulary": "practice", "partOfSpeech": "n", "chinese": "慣例;習慣;開業"}, {"vocabulary": "conclude", "partOfSpeech": "vt", "chinese": "下結論"}, {"vocabulary": "enable", "partOfSpeech": "vt", "chinese": "使能夠"}, {"vocabulary": "vehicle", "partOfSpeech": "n", "chinese": "車輛;(陸上)交通工具"}, {"vocabulary": "warn", "partOfSpeech": "vt", "chinese": "警告，告誡"}, {"vocabulary": "surround", "partOfSpeech": "vt", "chinese": "圍繞"}, {"vocabulary": "afford", "partOfSpeech": "vt", "chinese": "負擔得起"}, {"vocabulary": "affordable", "partOfSpeech": "adj", "chinese": "負擔得起的"}, {"vocabulary": "missile", "partOfSpeech": "n", "chinese": "飛彈"}]}