{"vocabularies": [{"vocabulary": "portrait", "partOfSpeech": "n", "chinese": "肖像畫，詳細的描繪"}, {"vocabulary": "strip", "partOfSpeech": "n", "chinese": "長條"}, {"vocabulary": "strip", "partOfSpeech": "vt", "chinese": "脫掉;剝掉;脫衣服"}, {"vocabulary": "marble", "partOfSpeech": "n", "chinese": "大理石；彈珠"}, {"vocabulary": "laughter", "partOfSpeech": "n", "chinese": "笑聲、笑（不可數）"}, {"vocabulary": "pretend", "partOfSpeech": "v", "chinese": "假裝"}, {"vocabulary": "bless", "partOfSpeech": "v", "chinese": "祝福;神賜福"}, {"vocabulary": "be blessed with ~", "partOfSpeech": "", "chinese": "幸運地擁有、被賜予"}, {"vocabulary": "agriculture", "partOfSpeech": "n", "chinese": "農業"}, {"vocabulary": "dislike", "partOfSpeech": "v", "chinese": "不喜愛;厭惡"}, {"vocabulary": "native", "partOfSpeech": "adj", "chinese": "本土的;本國的;原生的"}, {"vocabulary": "native", "partOfSpeech": "n", "chinese": "本地人;原住民"}, {"vocabulary": "award", "partOfSpeech": "n", "chinese": "獎項"}, {"vocabulary": "award", "partOfSpeech": "vt", "chinese": "頒發;授予"}, {"vocabulary": "acceptable", "partOfSpeech": "adj", "chinese": "可接受的"}, {"vocabulary": "meaningful", "partOfSpeech": "adj", "chinese": "有意義的"}, {"vocabulary": "meaningless", "partOfSpeech": "adj", "chinese": "無意義的"}, {"vocabulary": "statue", "partOfSpeech": "n", "chinese": "雕像、塑像"}, {"vocabulary": "faint", "partOfSpeech": "adj", "chinese": "微弱的;模糊的"}, {"vocabulary": "faint", "partOfSpeech": "n/v", "chinese": "昏倒"}, {"vocabulary": "trick", "partOfSpeech": "n", "chinese": "把戲"}, {"vocabulary": "(to) trick sb. into doing sth.", "partOfSpeech": "", "chinese": "欺騙某人做某事"}, {"vocabulary": "tricky", "partOfSpeech": "adj", "chinese": "複雜的；棘手的"}, {"vocabulary": "communicate", "partOfSpeech": "v", "chinese": "溝通"}, {"vocabulary": "swell", "partOfSpeech": "v", "chinese": "腫脹"}, {"vocabulary": "swell", "partOfSpeech": "n", "chinese": "湧起(海浪;情緒)"}, {"vocabulary": "swollen", "partOfSpeech": "adj", "chinese": "腫脹的"}, {"vocabulary": "rocket", "partOfSpeech": "n", "chinese": "火箭"}, {"vocabulary": "charm", "partOfSpeech": "n", "chinese": "吸引力;魔力;符咒"}, {"vocabulary": "charm", "partOfSpeech": "vt", "chinese": "迷住;使陶醉;行魔法"}, {"vocabulary": "charming", "partOfSpeech": "adj", "chinese": "迷人的;有吸引力的"}, {"vocabulary": "knight", "partOfSpeech": "n", "chinese": "騎士"}, {"vocabulary": "crispy", "partOfSpeech": "adj", "chinese": "酥脆的"}, {"vocabulary": "gang", "partOfSpeech": "n", "chinese": "幫派"}, {"vocabulary": "gang", "partOfSpeech": "vi", "chinese": "結黨;聯合"}, {"vocabulary": "thread", "partOfSpeech": "n", "chinese": "線"}, {"vocabulary": "march", "partOfSpeech": "n", "chinese": "行軍;長途跋涉;示威遊行"}, {"vocabulary": "explode", "partOfSpeech": "v", "chinese": "爆炸"}, {"vocabulary": "routine", "partOfSpeech": "n", "chinese": "例行公事"}, {"vocabulary": "routine", "partOfSpeech": "adj", "chinese": "例行性的;通常的"}, {"vocabulary": "regret", "partOfSpeech": "vt", "chinese": "後悔"}, {"vocabulary": "regret", "partOfSpeech": "n", "chinese": "惋惜;遺憾"}, {"vocabulary": "represent", "partOfSpeech": "v", "chinese": "代表"}, {"vocabulary": "representative", "partOfSpeech": "adj", "chinese": "代表性的"}, {"vocabulary": "representative", "partOfSpeech": "n", "chinese": "代表;代理人"}, {"vocabulary": "fountain", "partOfSpeech": "n", "chinese": "噴泉"}, {"vocabulary": "youngster", "partOfSpeech": "n", "chinese": "年輕人"}, {"vocabulary": "faucet", "partOfSpeech": "n", "chinese": "水龍頭(=tap 英式)"}, {"vocabulary": "tap", "partOfSpeech": "v", "chinese": "輕拍;輕敲"}, {"vocabulary": "tap water", "partOfSpeech": "n", "chinese": "自來水"}, {"vocabulary": "race", "partOfSpeech": "v", "chinese": "競速"}, {"vocabulary": "race", "partOfSpeech": "n", "chinese": "比賽/種族"}, {"vocabulary": "racial discrimination", "partOfSpeech": "n", "chinese": "種族歧視"}, {"vocabulary": "risk", "partOfSpeech": "n", "chinese": "冒險;風險"}, {"vocabulary": "risk", "partOfSpeech": "v", "chinese": "冒險"}, {"vocabulary": "follower", "partOfSpeech": "n", "chinese": "追隨者;信徒"}, {"vocabulary": "following", "partOfSpeech": "n", "chinese": "一批追隨者;下列事物(或人員)"}, {"vocabulary": "champion", "partOfSpeech": "n", "chinese": "冠軍；優勝者"}, {"vocabulary": "interrupt", "partOfSpeech": "v", "chinese": "打斷"}, {"vocabulary": "twin", "partOfSpeech": "n", "chinese": "雙胞胎"}, {"vocabulary": "loose", "partOfSpeech": "adj", "chinese": "鬆的"}, {"vocabulary": "tight", "partOfSpeech": "adj", "chinese": "緊的"}, {"vocabulary": "designer", "partOfSpeech": "n", "chinese": "設計師"}]}